README.rst
setup.py
autobrowser/__init__.py
autobrowser/probe.py
autobrowser/utility.py
autobrowser.egg-info/PKG-INFO
autobrowser.egg-info/SOURCES.txt
autobrowser.egg-info/dependency_links.txt
autobrowser.egg-info/requires.txt
autobrowser.egg-info/top_level.txt