Metadata-Version: 1.1
Name: autobrowser
Version: 0.2.0
Summary: Toolset for automated browsing
Home-page: https://github.com/sgzsh269/autobrowser
Author: Sagar Nilesh Shah
Author-email: shah.sagar.nilesh@gmail.com
License: MIT
Keywords: automation web browser
Platform: UNKNOWN
Classifier: Development Status :: 5 - Production/Stable
Classifier: Intended Audience :: Developers
Classifier: License :: OSI Approved :: MIT License
Classifier: Programming Language :: Python
Classifier: Programming Language :: Python :: 2.7
